fuxi/__core.cpython-39-x86_64-linux-gnu.so
fuxi/__core/__init__.pyi
fuxi/__core/backtest.pyi
fuxi/__core/base.pyi
fuxi/__core/code.pyi
fuxi/__core/context.pyi
fuxi/__core/market.pyi
fuxi/__core/order.pyi
fuxi/__core/position.pyi
fuxi/__init__.py
fuxi/strategy.py
fuxi_quant-0.0.6.dist-info/METADATA
fuxi_quant-0.0.6.dist-info/WHEEL
fuxi_quant-0.0.6.dist-info/licenses/LICENSE
fuxi_quant-0.0.6.dist-info/RECORD
