Metadata-Version: 2.4
Name: fuxi-quant
Version: 0.0.6
Classifier: Programming Language :: Rust
Classifier: Programming Language :: Python :: Implementation :: CPython
Classifier: Programming Language :: Python :: Implementation :: PyPy
Requires-Dist: polars[all]==1.34.0
Requires-Dist: ta-lib==0.6.7
Requires-Dist: numpy==2.3.3
Requires-Dist: setproctitle==1.3.7
License-File: LICENSE
Keywords: quant,trading,backtest,crypto
Author-email: Husky <husky.robot.dog@gmail.com>
Requires-Python: >=3.8
